zkeys.py
zkeys-0.2.0.dist-info/LICENSE
zkeys-0.2.0.dist-info/METADATA
zkeys-0.2.0.dist-info/WHEEL
zkeys-0.2.0.dist-info/entry_points.txt
zkeys-0.2.0.dist-info/top_level.txt
zkeys-0.2.0.dist-info/RECORD
